<?xml version='1.0' encoding='UTF-8'?><tasks>
<task>
<tasktitle>none</tasktitle>
<taskdescription>none</taskdescription>
<taskduedate>none</taskduedate>
<taskpriority>none</taskpriority>
<taskid>none</taskid>
</task>
<task>
<tasktitle>none</tasktitle>
<taskdescription>none</taskdescription>
<taskduedate>none</taskduedate>
<taskpriority>none</taskpriority>
<taskid>none</taskid>
</task>
<task>
<title>appointment</title>
<description>none</description>
<duedate>2025-02-20</duedate>
<priority>low</priority>
</task>
<task>
<tasktitle>appointment</tasktitle>
<taskdescription>none</taskdescription>
<taskduedate>2025-02-20</taskduedate>
<taskpriority>low</taskpriority>
</task>
<task>
<tasktitle>appointment</tasktitle>
<taskdescription>none</taskdescription>
<taskduedate>2025-02-20</taskduedate>
<taskpriority>low</taskpriority>
</task>
<task>
<tasktitle>appointment</tasktitle>
<taskdescription>none</taskdescription>
<taskduedate>2025-02-20</taskduedate>
<taskpriority>low</taskpriority>
</task>
<task>
<tasktitle>appointment</tasktitle>
<taskdescription>none</taskdescription>
<taskduedate>2025-02-20</taskduedate>
<taskpriority>low</taskpriority>
</task>
<task>
<tasktitle>appointment</tasktitle>
<taskdescription>none</taskdescription>
<taskduedate>2025-02-20</taskduedate>
<taskpriority>low</taskpriority>
</task>
<task>
<tasktitle>appointment</tasktitle>
<taskdescription>none</taskdescription>
<taskduedate>2025-02-20</taskduedate>
<taskpriority>low</taskpriority>
</task>
<task>
<tasktitle>appointment</tasktitle>
<taskdescription>none</taskdescription>
<taskduedate>2025-02-20</taskduedate>
<taskpriority>low</taskpriority>
</task>
<task>
<tasktitle>appointment</tasktitle>
<taskdescription>none</taskdescription>
<taskduedate>2025-02-20</taskduedate>
<taskpriority>low</taskpriority>
</task>
<task>
<tasktitle>appointment</tasktitle>
<taskdescription>none</taskdescription>
<taskduedate>2025-02-20</taskduedate>
<taskpriority>low</taskpriority>
</task>
</tasks>